sglang/README.md
sglang/__init__.py
sglang/_version.py
sglang/bench_offline_throughput.py
sglang/bench_one_batch.py
sglang/bench_one_batch_server.py
sglang/bench_serving.py
sglang/check_env.py
sglang/compile_deep_gemm.py
sglang/global_config.py
sglang/launch_server.py
sglang/profiler.py
sglang/utils.py
sglang/version.py
sglang/cli/__init__.py
sglang/cli/generate.py
sglang/cli/main.py
sglang/cli/serve.py
sglang/cli/utils.py
sglang/eval/llama3_eval.py
sglang/eval/loogle_eval.py
sglang/jit_kernel/.clang-format
sglang/jit_kernel/__main__.py
sglang/jit_kernel/add_constant.py
sglang/jit_kernel/cuda_wait_value.py
sglang/jit_kernel/hicache.py
sglang/jit_kernel/norm.py
sglang/jit_kernel/per_tensor_quant_fp8.py
sglang/jit_kernel/utils.py
sglang/jit_kernel/benchmark/bench_per_tensor_quant_fp8.py
sglang/jit_kernel/benchmark/bench_qknorm.py
sglang/jit_kernel/csrc/add_constant.cuh
sglang/jit_kernel/csrc/cuda_wait_value.cuh
sglang/jit_kernel/csrc/hicache.cuh
sglang/jit_kernel/csrc/norm.cuh
sglang/jit_kernel/csrc/test_utils.h
sglang/jit_kernel/csrc/gemm/per_tensor_quant_fp8.cuh
sglang/jit_kernel/include/sgl_kernel/fp8_utils.cuh
sglang/jit_kernel/include/sgl_kernel/runtime.cuh
sglang/jit_kernel/include/sgl_kernel/tensor.h
sglang/jit_kernel/include/sgl_kernel/utils.cuh
sglang/jit_kernel/include/sgl_kernel/utils.h
sglang/jit_kernel/include/sgl_kernel/warp.cuh
sglang/jit_kernel/tests/test_add_constant.py
sglang/jit_kernel/tests/test_per_tensor_quant_fp8.py
sglang/jit_kernel/tests/test_qknorm.py
sglang/lang/api.py
sglang/lang/chat_template.py
sglang/lang/choices.py
sglang/lang/interpreter.py
sglang/lang/ir.py
sglang/lang/tracer.py
sglang/lang/backend/anthropic.py
sglang/lang/backend/base_backend.py
sglang/lang/backend/litellm.py
sglang/lang/backend/openai.py
sglang/lang/backend/runtime_endpoint.py
sglang/lang/backend/vertexai.py
sglang/multimodal_gen/README.md
sglang/multimodal_gen/__init__.py
sglang/multimodal_gen/envs.py
sglang/multimodal_gen/registry.py
sglang-0.5.7.dist-info/licenses/LICENSE
sglang-0.5.7.dist-info/METADATA
sglang-0.5.7.dist-info/WHEEL
sglang-0.5.7.dist-info/entry_points.txt
sglang-0.5.7.dist-info/top_level.txt
sglang-0.5.7.dist-info/RECORD
