Metadata-Version: 2.4
Name: sglang
Version: 0.5.7
Summary: SGLang is a fast serving framework for large language models and vision language models.
License:                                  Apache License
Project-URL: Homepage, https://github.com/sgl-project/sglang
Project-URL: Bug Tracker, https://github.com/sgl-project/sglang/issues
Classifier: Programming Language :: Python :: 3
Classifier: License :: OSI Approved :: Apache Software License
Requires-Python: >=3.10
License-File: LICENSE
Requires-Dist: IPython
Requires-Dist: aiohttp
Requires-Dist: anthropic>=0.20.0
Requires-Dist: av; sys_platform == "linux" and (platform_machine == "aarch64" or platform_machine == "arm64" and platform_machine == "armv7l")
Requires-Dist: blobfile==3.0.0
Requires-Dist: build
Requires-Dist: compressed-tensors
Requires-Dist: cuda-python
Requires-Dist: decord2
Requires-Dist: datasets
Requires-Dist: einops
Requires-Dist: fastapi
Requires-Dist: flashinfer_python==0.5.3
Requires-Dist: flashinfer_cubin==0.5.3
Requires-Dist: gguf
Requires-Dist: hf_transfer
Requires-Dist: huggingface_hub
Requires-Dist: interegular
Requires-Dist: llguidance<0.8.0,>=0.7.11
Requires-Dist: modelscope
Requires-Dist: msgspec
Requires-Dist: ninja
Requires-Dist: numpy
Requires-Dist: nvidia-cutlass-dsl==4.2.1
Requires-Dist: nvidia-ml-py
Requires-Dist: openai-harmony==0.0.4
Requires-Dist: openai==2.6.1
Requires-Dist: orjson
Requires-Dist: outlines==0.1.11
Requires-Dist: packaging
Requires-Dist: partial_json_parser
Requires-Dist: pillow
Requires-Dist: prometheus-client>=0.20.0
Requires-Dist: psutil
Requires-Dist: py-spy
Requires-Dist: pybase64
Requires-Dist: pydantic
Requires-Dist: python-multipart
Requires-Dist: pyzmq>=25.1.2
Requires-Dist: requests
Requires-Dist: scipy
Requires-Dist: sentencepiece
Requires-Dist: setproctitle
Requires-Dist: sgl-kernel==0.3.20
Requires-Dist: soundfile==0.13.1
Requires-Dist: tiktoken
Requires-Dist: timm==1.0.16
Requires-Dist: torch_memory_saver==0.0.9
Requires-Dist: torch==2.9.1
Requires-Dist: torchaudio==2.9.1
Requires-Dist: torchcodec==0.8.0; sys_platform != "linux" or (sys_platform == "linux" and platform_machine != "aarch64" and platform_machine != "arm64" and platform_machine != "armv7l")
Requires-Dist: torchvision
Requires-Dist: torchao==0.9.0
Requires-Dist: tqdm
Requires-Dist: transformers==4.57.1
Requires-Dist: uvicorn
Requires-Dist: uvloop
Requires-Dist: xgrammar==0.1.27
Requires-Dist: grpcio==1.75.1
Requires-Dist: grpcio-tools==1.75.1
Requires-Dist: grpcio-reflection==1.75.1
Requires-Dist: grpcio-health-checking==1.75.1
Provides-Extra: checkpoint-engine
Requires-Dist: checkpoint-engine==0.1.2; extra == "checkpoint-engine"
Provides-Extra: diffusion
Requires-Dist: PyYAML==6.0.1; extra == "diffusion"
Requires-Dist: cloudpickle; extra == "diffusion"
Requires-Dist: diffusers==0.36.0; extra == "diffusion"
Requires-Dist: imageio==2.36.0; extra == "diffusion"
Requires-Dist: imageio-ffmpeg==0.5.1; extra == "diffusion"
Requires-Dist: moviepy>=2.0.0; extra == "diffusion"
Requires-Dist: opencv-python-headless==4.10.0.84; extra == "diffusion"
Requires-Dist: remote-pdb; extra == "diffusion"
Requires-Dist: st_attn==0.0.7; extra == "diffusion"
Requires-Dist: vsa==0.0.4; extra == "diffusion"
Requires-Dist: yunchang==0.6.3.post1; extra == "diffusion"
Requires-Dist: runai_model_streamer; extra == "diffusion"
Requires-Dist: cache-dit==1.1.8; extra == "diffusion"
Provides-Extra: tracing
Requires-Dist: opentelemetry-api; extra == "tracing"
Requires-Dist: opentelemetry-exporter-otlp; extra == "tracing"
Requires-Dist: opentelemetry-exporter-otlp-proto-grpc; extra == "tracing"
Requires-Dist: opentelemetry-sdk; extra == "tracing"
Provides-Extra: test
Requires-Dist: accelerate; extra == "test"
Requires-Dist: bitsandbytes; extra == "test"
Requires-Dist: expecttest; extra == "test"
Requires-Dist: jsonlines; extra == "test"
Requires-Dist: matplotlib; extra == "test"
Requires-Dist: pandas; extra == "test"
Requires-Dist: parameterized; extra == "test"
Requires-Dist: peft; extra == "test"
Requires-Dist: pytest; extra == "test"
Requires-Dist: sentence_transformers; extra == "test"
Requires-Dist: tabulate; extra == "test"
Provides-Extra: dev
Requires-Dist: sglang[test]; extra == "dev"
Dynamic: license-file
